ddodoga/__init__.py
ddodoga/function.py
pypiEX/__init__.py
pypiEX/function.py
ddodoga-1.0.0.dist-info/METADATA
ddodoga-1.0.0.dist-info/WHEEL
ddodoga-1.0.0.dist-info/top_level.txt
ddodoga-1.0.0.dist-info/RECORD
