Metadata-Version: 2.1
Name: ddodoga
Version: 1.0.0
Summary: exmple
Home-page: 
Author: yoda
Author-email: zza0423@gmail.com
License: MIT
Requires-Python: >=3
Requires-Dist: yfinance
